hfirstdemo.py
hfirstdemo-0.1.0.dist-info/METADATA
hfirstdemo-0.1.0.dist-info/WHEEL
hfirstdemo-0.1.0.dist-info/top_level.txt
hfirstdemo-0.1.0.dist-info/RECORD
