Metadata-Version: 2.1
Name: hfirstdemo
Version: 0.1.0
Summary: My first Python package
Home-page: https://github.com/hydong/hfirstdemo
Author: xgsj-hyd
Author-email: 455059546@qq.com
License: UNKNOWN
Platform: UNKNOWN
